pymemesuite-0.1.0a4.dist-info/RECORD
pymemesuite-0.1.0a4.dist-info/WHEEL
pymemesuite-0.1.0a4.dist-info/COPYING
pymemesuite-0.1.0a4.dist-info/top_level.txt
pymemesuite-0.1.0a4.dist-info/METADATA
pymemesuite/common.pxd
pymemesuite/cisml.pxd
pymemesuite/_globals.c
pymemesuite/common.cpython-38-darwin.so
pymemesuite/errors.pyx
pymemesuite/fimo.cpython-38-darwin.so
pymemesuite/cisml.cpython-38-darwin.so
pymemesuite/__init__.py
pymemesuite/fimo.pyx
pymemesuite/_exceptions.c
pymemesuite/errors.cpython-38-darwin.so
pymemesuite/common.pyx
pymemesuite/cisml.pyx
pymemesuite/tests/requirements.txt
pymemesuite/tests/__init__.py
pymemesuite/tests/test_doctest.py
pymemesuite/tests/test_fimo.py
pymemesuite/tests/fasta.py
pymemesuite/tests/test_common/__init__.py
pymemesuite/tests/test_common/test_alphabet.py
pymemesuite/tests/test_common/test_background.py
pymemesuite/tests/test_common/test_motif_file.py
pymemesuite/tests/data/__init__.py
pymemesuite/tests/data/fimo/results.tsv
pymemesuite/tests/data/fimo/results-norc.tsv
pymemesuite/tests/data/fimo/__init__.py
pymemesuite/tests/data/fimo/mibig-genes.fna
pymemesuite/tests/data/fimo/prodoric_mx000001_meme.txt
