Metadata-Version: 2.1
Name: pymemesuite
Version: 0.1.0a4
Summary: Cython bindings and Python interface to the MEME suite.
Home-page: https://github.com/althonos/pymemesuite
Author: Martin Larralde
Author-email: Martin Larralde <martin.larralde@embl.de>
License: MIT License
Project-URL: Bug Tracker, https://github.com/althonos/pymemesuite/issues
Project-URL: Changelog, https://github.com/althonos/pymemesuite/blob/master/CHANGELOG.md
Project-URL: Coverage, https://codecov.io/gh/althonos/pymemesuite/
Project-URL: Builds, https://github.com/althonos/pymemesuite/actions
Project-URL: PyPI, https://pypi.org/project/pymemesuite
Keywords: bioinformatics,motif,sequence,enrichment,logo
Platform: posix
Classifier: Development Status :: 3 - Alpha
Classifier: Intended Audience :: Developers
Classifier: Intended Audience :: Science/Research
Classifier: License :: OSI Approved :: MIT License
Classifier: Programming Language :: C
Classifier: Programming Language :: Cython
Classifier: Programming Language :: Python :: 3.7
Classifier: Programming Language :: Python :: 3.8
Classifier: Programming Language :: Python :: 3.9
Classifier: Programming Language :: Python :: 3.10
Classifier: Programming Language :: Python :: 3.11
Classifier: Programming Language :: Python :: 3.12
Classifier: Programming Language :: Python :: 3.13
Classifier: Programming Language :: Python :: Implementation :: CPython
Classifier: Programming Language :: Python :: Implementation :: PyPy
Classifier: Topic :: Scientific/Engineering :: Bio-Informatics
Classifier: Topic :: Scientific/Engineering :: Medical Science Apps.
Classifier: Typing :: Typed
Requires-Python: >=3.7
License-File: COPYING
Provides-Extra: test
Requires-Dist: importlib-resources; python_version < "3.9" and extra == "test"
